katrain/__init__.py
katrain/__main__.py
katrain/config.json
katrain/gui.kv
katrain/popups.kv
katrain/KataGo/OpenCL.dll
katrain/KataGo/__init__.py
katrain/KataGo/analysis_config.cfg
katrain/KataGo/cacert.pem
katrain/KataGo/contribute_config.cfg
katrain/KataGo/katago
katrain/KataGo/katago.exe
katrain/KataGo/libcrypto-1_1-x64.dll
katrain/KataGo/libcrypto-3-x64.dll
katrain/KataGo/libssl-1_1-x64.dll
katrain/KataGo/libssl-3-x64.dll
katrain/KataGo/libz.dll
katrain/KataGo/libzip.dll
katrain/KataGo/msvcp140.dll
katrain/KataGo/msvcp140_1.dll
katrain/KataGo/msvcp140_2.dll
katrain/KataGo/msvcp140_atomic_wait.dll
katrain/KataGo/msvcp140_codecvt_ids.dll
katrain/KataGo/vcruntime140.dll
katrain/KataGo/vcruntime140_1.dll
katrain/core/__init__.py
katrain/core/ai.py
katrain/core/base_katrain.py
katrain/core/constants.py
katrain/core/contribute_engine.py
katrain/core/engine.py
katrain/core/game.py
katrain/core/game_node.py
katrain/core/lang.py
katrain/core/sgf_parser.py
katrain/core/tsumego_frame.py
katrain/core/utils.py
katrain/fonts/NotoSans-Regular.ttf
katrain/fonts/NotoSansCJKsc-Regular.otf
katrain/fonts/NotoSansJP-Regular.otf
katrain/fonts/OFL.txt
katrain/fonts/__init__.py
katrain/fonts/digital-7 (mono).ttf
katrain/gui/__init__.py
katrain/gui/badukpan.py
katrain/gui/controlspanel.py
katrain/gui/kivyutils.py
katrain/gui/popups.py
katrain/gui/sound.py
katrain/gui/theme.py
katrain/gui/widgets/__init__.py
katrain/gui/widgets/filebrowser.py
katrain/gui/widgets/graph.py
katrain/gui/widgets/movetree.py
katrain/gui/widgets/progress_loader.py
katrain/gui/widgets/selection_slider.py
katrain/i18n/__init__.py
katrain/i18n/locales/cn/LC_MESSAGES/katrain.mo
katrain/i18n/locales/cn/LC_MESSAGES/katrain.po
katrain/i18n/locales/de/LC_MESSAGES/katrain.mo
katrain/i18n/locales/de/LC_MESSAGES/katrain.po
katrain/i18n/locales/en/LC_MESSAGES/katrain.mo
katrain/i18n/locales/en/LC_MESSAGES/katrain.po
katrain/i18n/locales/es/LC_MESSAGES/katrain.mo
katrain/i18n/locales/es/LC_MESSAGES/katrain.po
katrain-1.17.0.dist-info/METADATA
katrain-1.17.0.dist-info/WHEEL
katrain-1.17.0.dist-info/entry_points.txt
katrain-1.17.0.dist-info/licenses/LICENSE
katrain-1.17.0.dist-info/RECORD
