Metadata-Version: 2.4
Name: KaTrain
Version: 1.17.0
Summary: Go/Baduk/Weiqi playing and teaching app with a variety of AIs
Project-URL: Homepage, https://github.com/sanderland/katrain
Author: Sander Land
License-Expression: MIT
License-File: LICENSE
Classifier: Development Status :: 5 - Production/Stable
Classifier: Operating System :: Microsoft :: Windows
Classifier: Operating System :: POSIX :: Linux
Classifier: Programming Language :: Python :: 3
Classifier: Topic :: Games/Entertainment :: Board Games
Requires-Python: <3.13,>=3.9
Requires-Dist: chardet<6,>=5.2.0
Requires-Dist: docutils>=0.21.2
Requires-Dist: ffpyplayer>=4.5.1
Requires-Dist: kivy>=2.3.1
Requires-Dist: kivymd==0.104.1
Requires-Dist: pygame~=2.0; platform_system == 'Darwin'
Requires-Dist: screeninfo<0.9,>=0.8.1; platform_system != 'Darwin'
Requires-Dist: urllib3>=2.2.2
